flask_oidc_ext/__init__.py
flask_oidc_ext/discovery.py
flask_oidc_ext/registration.py
flask_oidc_ext/registration_util.py
flask_oidc_ext-1.4.5.dist-info/LICENSE.txt
flask_oidc_ext-1.4.5.dist-info/METADATA
flask_oidc_ext-1.4.5.dist-info/WHEEL
flask_oidc_ext-1.4.5.dist-info/entry_points.txt
flask_oidc_ext-1.4.5.dist-info/top_level.txt
flask_oidc_ext-1.4.5.dist-info/RECORD
