Metadata-Version: 2.1
Name: flask-oidc-ext
Version: 1.4.5
Summary: OpenID Connect extension for Flask
Home-page: https://github.com/svintit/flask-oidc-ext
Author: Erica Ehrhardt, Patrick Uiterwijk, Traian Svinti
Author-email: traian.svinti@gmail.com
Classifier: Environment :: Web Environment
Classifier: Framework :: Flask
Classifier: Intended Audience :: Developers
Classifier: License :: OSI Approved :: BSD License
Classifier: Operating System :: OS Independent
Classifier: Programming Language :: Python
Classifier: Programming Language :: Python :: 2
Classifier: Programming Language :: Python :: 2.6
Classifier: Programming Language :: Python :: 2.7
Classifier: Programming Language :: Python :: 3
Classifier: Programming Language :: Python :: 3.3
Classifier: Programming Language :: Python :: 3.4
Classifier: Topic :: Internet :: WWW/HTTP :: Dynamic Content
Classifier: Topic :: Software Development :: Libraries :: Python Modules
License-File: LICENSE.txt
Requires-Dist: Flask
Requires-Dist: authlib
Requires-Dist: oauth2client
Requires-Dist: six
